geoexpress_wrapper/__init__.py
geoexpress_wrapper/config.py
geoexpress_wrapper/encoder.py
geoexpress_wrapper/exceptions.py
geoexpress_wrapper/license.py
geoexpress_wrapper-0.1.0.dist-info/licenses/license.py
geoexpress_wrapper-0.1.0.dist-info/METADATA
geoexpress_wrapper-0.1.0.dist-info/WHEEL
geoexpress_wrapper-0.1.0.dist-info/top_level.txt
geoexpress_wrapper-0.1.0.dist-info/RECORD
