Metadata-Version: 2.4
Name: geoexpress-wrapper
Version: 0.1.0
Summary: Python wrapper for LizardTech GeoExpress CLI (license required)
Author-email: Vibudh Bhatnagar <info@geowgs84.com>
License-Expression: MIT
Requires-Python: >=3.8
License-File: license.py
Dynamic: license-file
